{
  "version": "5.0.1",
  "flags": {},
  "shapes": [
    {
      "label": "leading edge;erosion;coating or LEP only",
      "points": [
        [
          4037.9629629629626,
          1831.6666666666665
        ],
        [
          4645.37037037037,
          2187.222222222222
        ],
        [
          4663.888888888889,
          2127.962962962963
        ],
        [
          4108.333333333333,
          1768.7037037037037
        ]
      ],
      "group_id": null,
      "shape_type": "polygon",
      "flags": {}
    }
  ],
  "imagePath": "12_ef6abcae-d040-42a3-8d8b-fc015e0cba13.jpg",
  "imageData": null,
  "imageHeight": 3632,
  "imageWidth": 5456
}