{
  "version": "5.0.1",
  "flags": {},
  "shapes": [
    {
      "label": "add-on;markings;lifting point",
      "points": [
        [
          1139.9999999999998,
          2211.3043478260865
        ],
        [
          1190.4347826086955,
          2210.4347826086955
        ],
        [
          1295.6521739130433,
          2220.869565217391
        ],
        [
          1307.8260869565215,
          2214.782608695652
        ],
        [
          1361.7391304347825,
          2108.695652173913
        ],
        [
          1266.086956521739,
          2094.782608695652
        ],
        [
          1199.1304347826085,
          2098.260869565217
        ],
        [
          1224.3478260869563,
          2053.0434782608695
        ],
        [
          1205.2173913043478,
          2066.95652173913
        ],
        [
          1142.6086956521738,
          2158.260869565217
        ],
        [
          1127.8260869565215,
          2200.869565217391
        ],
        [
          1109.5652173913043,
          2256.5217391304345
        ],
        [
          1115.6521739130433,
          2251.3043478260865
        ]
      ],
      "group_id": null,
      "shape_type": "polygon",
      "flags": {}
    }
  ],
  "imagePath": "13_22b44379-5dfd-4f1f-bc0d-cd6644f76099.jpg",
  "imageData": null,
  "imageHeight": 3632,
  "imageWidth": 5456
}